image_processing/__init__.py
image_processing/processing/__init__.py
image_processing/processing/combination.py
image_processing/processing/transformation.py
image_processing/utils/__init__.py
image_processing/utils/io.py
image_processing/utils/plot.py
murilo_teste_pacote-0.0.1.dist-info/METADATA
murilo_teste_pacote-0.0.1.dist-info/WHEEL
murilo_teste_pacote-0.0.1.dist-info/top_level.txt
murilo_teste_pacote-0.0.1.dist-info/RECORD
