Metadata-Version: 2.1
Name: murilo-teste-pacote
Version: 0.0.1
Summary: My short description
Home-page: https://github.com/murilo-silva-marim
Author: Murilo
Author-email: murilo12391@hotmail.com
License: UNKNOWN
Platform: UNKNOWN
Requires-Python: >=3.8
